wopo/__init__.py
wopo/agent.py
wopo/consolidator.py
wopo/minifier.py
wopo/prompts.py
wopo/wopo.py
wopo-0.0.2.dist-info/LICENSE.txt
wopo-0.0.2.dist-info/METADATA
wopo-0.0.2.dist-info/WHEEL
wopo-0.0.2.dist-info/top_level.txt
wopo-0.0.2.dist-info/RECORD
