Metadata-Version: 2.1
Name: wopo
Version: 0.0.2
Summary: wordlabs open prompt optimiser: Automatic prompt optimisation
Home-page: https://github.com/wordlabs-io/wopo
Author: wordlabs.io
Author-email: <tanishk.kithannae@wordlabs.io>
License: LICENSE.txt
Keywords: python,nlp,prompt,optimisation
Classifier: Development Status :: 3 - Alpha
Classifier: Intended Audience :: Developers
Classifier: Programming Language :: Python :: 3
Classifier: Operating System :: Unix
Classifier: Operating System :: MacOS :: MacOS X
Classifier: Operating System :: Microsoft :: Windows
License-File: LICENSE.txt
Requires-Dist: tqdm
Requires-Dist: pandas
